[
    {
        "title": "2016 Presidency election night coverage",
        "image": "https://picsum.photos/600/600/?random",
        "id": "id-project"
    },
    {
        "title": "2016 Presidency election night coverage",
        "image": "https://picsum.photos/600/600/?random",
        "id": "id-project"
    },
    {
        "title": "2016 Presidency election night coverage",
        "image": "https://picsum.photos/600/600/?random",
        "id": "id-project"
    },
    {
        "title": "2016 Presidency election night coverage",
        "image": "https://picsum.photos/600/600/?random",
        "id": "id-project"
    },
    {
        "title": "2016 Presidency election night coverage",
        "image": "https://picsum.photos/600/600/?random",
        "id": "id-project"
    },
    {
        "title": "2016 Presidency election night coverage",
        "image": "https://picsum.photos/600/600/?random",
        "id": "id-project"
    },
    {
        "title": "2016 Presidency election night coverage",
        "image": "https://picsum.photos/600/600/?random",
        "id": "id-project"
    },
    {
        "title": "2016 Presidency election night coverage",
        "image": "https://picsum.photos/600/600/?random",
        "id": "id-project"
    }
]